KissDownloader-2.dist-info/DESCRIPTION.rst
KissDownloader-2.dist-info/METADATA
KissDownloader-2.dist-info/RECORD
KissDownloader-2.dist-info/WHEEL
KissDownloader-2.dist-info/metadata.json
KissDownloader-2.dist-info/top_level.txt
Program Files/PhantomJS/phantomjs.exe
scr/FINAL.py
scr/VRSKacq.py
scr/VRSKd.py
scr/__init__.py
