Metadata-Version: 2.0
Name: KissDownloader
Version: 2
Summary: A kisscartoon/kissanime downloader
Home-page: UNKNOWN
Author: Vriska
Author-email: anirudhgan@gmail.com
License: UNKNOWN
Platform: UNKNOWN
Requires-Dist: bs4
Requires-Dist: cfscrape
Requires-Dist: requests
